syracuse/__init__.py
syracuse/core.py
syracuse/drawing.py
syracuse/sequences.py
syracuse-0.4.0.dist-info/LICENSE.md
syracuse-0.4.0.dist-info/WHEEL
syracuse-0.4.0.dist-info/METADATA
syracuse-0.4.0.dist-info/RECORD
