Metadata-Version: 2.1
Name: syracuse
Version: 0.4.0
Summary: The Syracuse problem (aka Collatz conjecture) library
Home-page: https://github.com/devfred78/syracuse
License: MIT
Keywords: syracuse,collatz,3n+1,conjecture,ulan,kakutani,thwaites,hasse,hailstone,wondrous
Author: devfred78
Author-email: 97401939+devfred78@users.noreply.github.com
Requires-Python: >=3.11,<3.12
Classifier: Development Status :: 3 - Alpha
Classifier: Intended Audience :: Education
Classifier: License :: OSI Approved :: MIT License
Classifier: Operating System :: OS Independent
Classifier: Programming Language :: Python :: 3
Classifier: Programming Language :: Python :: 3.11
Classifier: Topic :: Scientific/Engineering :: Mathematics
Requires-Dist: gmpy2 (>=2.1.5,<3.0.0)
Requires-Dist: matplotlib (>=3.6,<3.7)
Requires-Dist: more-itertools (>=9.1.0,<10.0.0)
Requires-Dist: networkx[default] (>=3.0,<4.0)
Requires-Dist: numpy (>=1.24,<1.25)
Requires-Dist: pydot (>=1.4.2,<2.0.0)
Project-URL: Documentation, https://devfred78.github.io/syracuse/
Project-URL: Repository, https://github.com/devfred78/syracuse
